{
  "Recettes": [
    {
      "id": "1",
      "titre": "Couscous Royal",
      "pays": "Maroc",
      "categorie": "Plat traditionnel",
      "image": "https://res.cloudinary.com/djnqthl9y/image/upload/v1764082671/2148081051_hgdtly.jpg",
      "description": "Un plat marocain emblématique composé de semoule légère, de légumes mijotés et d'une variété de viandes.",
      "ingredients": [
        "500g de semoule de couscous",
        "Poulet, agneau et merguez",
        "Carottes, courgettes, navets, potiron",
        "Pois chiches",
        "Oignons",
        "Épices (ras el hanout, curcuma, gingembre)",
        "Huile d'olive"
      ],
      "etapes": [
        "Préparer la semoule et la travailler à la main.",
        "Faire revenir les oignons et les viandes dans l'huile.",
        "Ajouter les épices et les légumes.",
        "Laisser mijoter doucement.",
        "Servir la semoule dans un grand plat et disposer les légumes et viandes par-dessus."
      ]
    },
    {
      "id": "2",
      "titre": "Tajine de Poulet au Citron Confit",
      "description": "Un tajine classique marocain aux saveurs citronnées et parfumé à la coriandre.",
      "categorie": "Plat mijoté",
      "pays": "Maroc",
      "image": "https://res.cloudinary.com/djnqthl9y/image/upload/v1764081620/fried-chicken-with-rice-tomato-lemon_ro6oan.jpg",
      "ingredients": [
        "1 poulet coupé en morceaux",
        "Citron confit",
        "Olives vertes",
        "Ail et oignons",
        "Safran, gingembre, curcuma",
        "Coriandre fraîche"
      ],
      "etapes": [
        "Faire revenir le poulet avec les oignons et les épices.",
        "Ajouter le citron confit et un peu d'eau.",
        "Laisser cuire à feu doux dans un tajine.",
        "Ajouter les olives en fin de cuisson.",
        "Servir chaud."
      ]
    },
    {
      "titre": "Pastilla au Poulet",
      "description": "Une pâtisserie salée-sucrée à base de feuilles de brick, de poulet parfumé et d’amandes.",
      "categorie": "Entrée / Plat",
      "pays": "Maroc",
      "image": "https://res.cloudinary.com/djnqthl9y/image/upload/v1764083536/40873_zpiyro.jpg",
      "ingredients": [
        "Feuilles de brick",
        "Poulet",
        "Oignons",
        "Amandes",
        "Cannelle",
        "Sucre glace",
        "Beurre"
      ],
      "etapes": [
        "Cuire le poulet avec les épices.",
        "Émietter la viande et mélanger avec les oignons.",
        "Ajouter les amandes sucrées.",
        "Monter la pastilla en couches.",
        "Cuire au four jusqu’à ce qu'elle soit dorée."
      ],
      "id": "3"
    },
    {
      "id": "4",
      "titre": "Pizza Margherita",
      "pays": "Italie",
      "categorie": "Plat rapide",
      "image": "https://res.cloudinary.com/djnqthl9y/image/upload/v1764083712/2150096953_wr2w1c.jpg",
      "description": "La pizza italienne par excellence avec tomate, mozzarella et basilic.",
      "ingredients": [
        "Pâte à pizza",
        "Sauce tomate",
        "Mozzarella",
        "Basilic frais",
        "Huile d’olive"
      ],
      "etapes": [
        "Étaler la pâte.",
        "Ajouter la sauce tomate et la mozzarella.",
        "Cuire au four à haute température.",
        "Garnir de basilic frais avant de servir."
      ]
    },
    {
      "titre": "Pâtes Carbonara",
      "description": "Un plat italien crémeux sans crème, à base d'œufs, de pecorino et de guanciale.",
      "categorie": "Pâtes",
      "pays": "Italie",
      "image": "https://res.cloudinary.com/djnqthl9y/image/upload/v1764083831/2149514171_sgf8mu.jpg",
      "ingredients": [
        "Spaghetti",
        "Guanciale",
        "Œufs",
        "Pecorino Romano",
        "Poivre noir"
      ],
      "etapes": [
        "Cuire les pâtes.",
        "Faire revenir le guanciale.",
        "Mélanger œufs et pecorino.",
        "Ajouter les pâtes chaudes hors du feu.",
        "Poivrer généreusement."
      ],
      "id": "5"
    },
    {
      "id": "6",
      "titre": "Lasagnes à la Bolognaise",
      "pays": "Italie",
      "categorie": "Plat au four",
      "image": "https://res.cloudinary.com/djnqthl9y/image/upload/v1764083947/2150690657_iaozop.jpg",
      "description": "Un gratin italien généreux composé de viande mijotée et de sauce béchamel.",
      "ingredients": [
        "Feuilles de lasagnes",
        "Viande hachée",
        "Tomates",
        "Béchamel",
        "Mozzarella"
      ],
      "etapes": [
        "Préparer la sauce bolognaise.",
        "Alterner couches de sauce, lasagnes et béchamel.",
        "Recouvrir de fromage.",
        "Cuire jusqu’à gratination."
      ]
    },
    {
      "id": "7",
      "titre": "Quiche Lorraine",
      "pays": "France",
      "categorie": "Entrée salée",
      "image": "https://res.cloudinary.com/djnqthl9y/image/upload/v1764084099/6268_xcixac.jpg",
      "description": "Une tarte salée à base de crème, œufs, lardons et fromage.",
      "ingredients": [
        "Pâte brisée",
        "Lardons",
        "Crème fraîche",
        "Œufs",
        "Gruyère"
      ],
      "etapes": [
        "Faire précuire la pâte.",
        "Préparer l'appareil œufs-crème.",
        "Ajouter les lardons.",
        "Cuire au four 30 minutes."
      ]
    },
    {
      "id": "8",
      "titre": "Bœuf Bourguignon",
      "pays": "France",
      "categorie": "Plat mijoté",
      "image": "https://res.cloudinary.com/djnqthl9y/image/upload/v1764084224/roast-chicken-liver-with-vegetables_ku7djn.jpg",
      "description": "Un ragoût français classique de bœuf mijoté au vin rouge.",
      "ingredients": [
        "Bœuf",
        "Carottes",
        "Oignons",
        "Vin rouge",
        "Champignons",
        "Thym et laurier"
      ],
      "etapes": [
        "Faire revenir la viande.",
        "Ajouter les légumes.",
        "Verser le vin rouge.",
        "Laisser mijoter 2 heures."
      ]
    },
    {
      "id": "9",
      "titre": "Ratatouille",
      "pays": "France",
      "categorie": "Plat végétarien",
      "image": "https://res.cloudinary.com/djnqthl9y/image/upload/v1764084407/hot-spicy-stew-eggplant-sweet-pepper-olives-capers-with-basil-leaves_u0phgx.jpg",
      "description": "Un mélange mijoté de légumes du sud de la France.",
      "ingredients": [
        "Aubergines",
        "Courgettes",
        "Poivrons",
        "Tomates",
        "Ail",
        "Herbes de Provence"
      ],
      "etapes": [
        "Couper tous les légumes.",
        "Faire revenir séparément.",
        "Assembler dans une cocotte.",
        "Mijoter 40 minutes."
      ]
    },
    {
      "id": "10",
      "titre": "Tiramisu Classique",
      "description": "Un dessert italien crémeux au café et au mascarpone.",
      "categorie": "Dessert",
      "pays": "Italie",
      "image": "https://res.cloudinary.com/djnqthl9y/image/upload/v1764084562/Tiramisu_Classique_saiunv.webp",
      "ingredients": [
        "Biscuits boudoirs",
        "Mascarpone",
        "Café fort",
        "Œufs",
        "Cacao"
      ],
      "etapes": [
        "Mélanger les jaunes d'œufs avec le mascarpone.",
        "Monter les blancs en neige.",
        "Assembler la crème.",
        "Tremper les biscuits dans le café.",
        "Monter en couches et réfrigérer."
      ]
    },
    {
      "id": "c1b5",
      "titre": "Pâtes au Beurre",
      "description": "jjjjjjjjj",
      "categorie": "plat",
      "pays": "maroc",
      "image": "https://res.cloudinary.com/dh6r1fw3q/image/upload/v1764862411/hfd4awmluktgbirhqhvd.jpg",
      "ingredients": [
        "Pâtes",
        "Beurre",
        "Sel",
        "Poivre"
      ],
      "etapes": [
        "const [errors, setErrors] = useState({})",
        "const [errors, setErrors] = useState({})",
        "const [errors, setErrors] = useState({})"
      ]
    }
  ]
}